tests/__init__.py
tests/test_main.py
tests/test_passwd.py
totalpass/__init__.py
totalpass/__main__.py
totalpass/__version__.py
totalpass/cirt.py
totalpass/core.py
totalpass/exceptions.py
totalpass/passwd.py
totalpass/scanner.py
totalpass/settings.py
totalpass/target.py
totalpass/addons/__init__.py
totalpass/addons/redis.py
totalpass/addons/snmp.py
totalpass/addons/ssh.py
totalpass/addons/telnet.py
totalpass/payloads/tiny.csv
totalpass/payloads/cirt/2wire inc/Wireless Routers.yml
totalpass/payloads/cirt/360 systems/Image Server 2000.yml
totalpass/payloads/cirt/3com/3CRWE52196.yml
totalpass/payloads/cirt/3com/AirConnect AP.yml
totalpass/payloads/cirt/3com/CellPlex.yml
totalpass/payloads/cirt/3com/CoreBuilder.yml
totalpass/payloads/cirt/3com/HiPerARC.yml
totalpass/payloads/cirt/3com/LANplex.yml
totalpass/payloads/cirt/3com/LinkSwitch.yml
totalpass/payloads/cirt/3com/N-A.yml
totalpass/payloads/cirt/3com/NetBuilder.yml
totalpass/payloads/cirt/3com/Office Connect ISDN Routers.yml
totalpass/payloads/cirt/3com/OfficeConnect Remote Router.yml
totalpass/payloads/cirt/3com/OfficeConnect Wireless AP.yml
totalpass/payloads/cirt/3com/Router.yml
totalpass/payloads/cirt/3com/SuperStack II Switch.yml
totalpass/payloads/cirt/3com/Superstack 3 switch.yml
totalpass/payloads/cirt/3com/US Robotics ADSL Router.yml
totalpass/payloads/cirt/3com/Wireless AP.yml
totalpass/payloads/cirt/3com/e960.yml
totalpass/payloads/cirt/3m/Volition.yml
totalpass/payloads/cirt/3m/Voliton.yml
totalpass/payloads/cirt/accelerated networks/DSL CPE and DSLAM.yml
totalpass/payloads/cirt/accton/CheetahChassis Workgroup Switch - telnet.yml
totalpass/payloads/cirt/accton/CheetahChassis Workgroup Switch - web.yml
totalpass/payloads/cirt/accton/CheetahChassis Workgroup Switch.yml
totalpass/payloads/cirt/accton/Gigabit Switches - ssh.yml
totalpass/payloads/cirt/accton/Gigabit Switches.yml
totalpass/payloads/cirt/accton/Wirelessrouter.yml
totalpass/payloads/cirt/acer/BIOS.yml
TotalPass-0.0.2.dist-info/LICENSE
TotalPass-0.0.2.dist-info/METADATA
TotalPass-0.0.2.dist-info/WHEEL
TotalPass-0.0.2.dist-info/entry_points.txt
TotalPass-0.0.2.dist-info/top_level.txt
TotalPass-0.0.2.dist-info/RECORD
