Metadata-Version: 2.1
Name: TotalPass
Version: 0.0.2
Summary: Defualt password scanner and searcher
Home-page: https://github.com/0xHJK/TotalPass
Author: HJK
Author-email: HJKdev@gmail.com
License: MIT License
Platform: UNKNOWN
Classifier: Development Status :: 4 - Beta
Classifier: Environment :: Console
Classifier: Intended Audience :: Developers
Classifier: Intended Audience :: End Users/Desktop
Classifier: License :: OSI Approved :: MIT License
Classifier: Operating System :: OS Independent
Classifier: Programming Language :: Python
Classifier: Programming Language :: Python :: 3
Classifier: Programming Language :: Python :: 3 :: Only
Classifier: Programming Language :: Python :: 3.7
Classifier: Programming Language :: Python :: 3.8
Classifier: Topic :: Security
Classifier: Topic :: Security :: Cryptography
Classifier: Topic :: Internet
Classifier: Topic :: System
Classifier: Topic :: Database
Classifier: Topic :: Utilities
Requires-Dist: redis
Requires-Dist: pysnmp
Requires-Dist: netaddr
Requires-Dist: click
Requires-Dist: pyyaml
Requires-Dist: paramiko
Requires-Dist: requests
